README.rst
setup.py
PedalPi_Raspberry_Physical.egg-info/PKG-INFO
PedalPi_Raspberry_Physical.egg-info/SOURCES.txt
PedalPi_Raspberry_Physical.egg-info/dependency_links.txt
PedalPi_Raspberry_Physical.egg-info/requires.txt
PedalPi_Raspberry_Physical.egg-info/top_level.txt
physical/__init__.py
physical/rotary_encoder.py
physical/liquidcristal/__init__.py
physical/liquidcristal/command.py
physical/liquidcristal/configuration.py
physical/liquidcristal/liquid_crystal.py
physical/liquidcristal/util.py
physical/sevensegments/__init__.py
physical/sevensegments/display_strategy.py
physical/sevensegments/multiplex_thread.py
physical/sevensegments/seven_segments.py
physical/sevensegments/seven_segments_dictionary.py
physical/sevensegments/text_write_strategy.py