Metadata-Version: 1.1
Name: PedalPi-Raspberry-Physical
Version: 0.2.0
Summary: Implementation of components that gpiozero does not yet support
Home-page: https://github.com/PedalPi/Raspberry-Physical
Author: Paulo Mateus Moura da Silva (SrMouraSilva)
Author-email: mateus.moura@hotmail.com
License: Apache Software License v2
Keywords: pedal-pi raspberry gpiozero
Platform: Linux
Classifier: Development Status :: 3 - Alpha
Classifier: Intended Audience :: Developers
Classifier: License :: OSI Approved :: Apache Software License
Classifier: Programming Language :: Python :: 3
